sirf_simind_connection/__init__.py
sirf_simind_connection/builders/__init__.py
sirf_simind_connection/builders/acquisition_builder.py
sirf_simind_connection/builders/image_builder.py
sirf_simind_connection/configs/__init__.py
sirf_simind_connection/converters/__init__.py
sirf_simind_connection/converters/attenuation.py
sirf_simind_connection/converters/dicom_to_stir.py
sirf_simind_connection/converters/simind_to_stir.py
sirf_simind_connection/core/__init__.py
sirf_simind_connection/core/components.py
sirf_simind_connection/core/config.py
sirf_simind_connection/core/projector.py
sirf_simind_connection/core/simulator.py
sirf_simind_connection/data/__init__.py
sirf_simind_connection/data/bone.atn
sirf_simind_connection/data/h2o.atn
sirf_simind_connection/utils/__init__.py
sirf_simind_connection/utils/io_utils.py
sirf_simind_connection/utils/simind_utils.py
sirf_simind_connection/utils/stir_utils.py
sirf_simind_connection-0.2.2.dist-info/licenses/LICENSE
sirf_simind_connection-0.2.2.dist-info/METADATA
sirf_simind_connection-0.2.2.dist-info/WHEEL
sirf_simind_connection-0.2.2.dist-info/top_level.txt
sirf_simind_connection-0.2.2.dist-info/RECORD
