Metadata-Version: 2.4
Name: sirf-simind-connection
Version: 0.2.2
Summary: A wrapper for SIRF and SIMIND for Monte Carlo SPECT simulations
Author-email: Sam Porter <sam.porter.18@ucl.ac.uk>, Rebecca Gillen <rebecca.gillen.18@ucl.ac.uk>, "Efstathios (Stahis) Varzakis" <efstathios.varzakis.22@ucl.ac.uk>
Maintainer-email: Sam Porter <sam.porter.18@ucl.ac.uk>
License: Apache-2.0
Project-URL: Homepage, https://github.com/samdporter/SIRF-SIMIND-Connection
Project-URL: Documentation, https://sirf-simind-connection.readthedocs.io/
Project-URL: Repository, https://github.com/samdporter/SIRF-SIMIND-Connection
Project-URL: Issues, https://github.com/samdporter/SIRF-SIMIND-Connection/issues
Keywords: SPECT,Monte Carlo,medical imaging,SIMIND,SIRF,STIR
Classifier: Development Status :: 4 - Beta
Classifier: Intended Audience :: Science/Research
Classifier: Topic :: Scientific/Engineering :: Medical Science Apps.
Classifier: License :: OSI Approved :: Apache Software License
Classifier: Programming Language :: Python :: 3
Classifier: Programming Language :: Python :: 3.9
Classifier: Programming Language :: Python :: 3.10
Classifier: Programming Language :: Python :: 3.11
Classifier: Programming Language :: Python :: 3.12
Requires-Python: >=3.9
License-File: LICENSE
Requires-Dist: numpy>=1.20.0
Requires-Dist: pydicom>=2.0.0
Requires-Dist: pyyaml>=5.4.0
Provides-Extra: dev
Requires-Dist: pytest>=6.0; extra == "dev"
Requires-Dist: pytest-cov; extra == "dev"
Requires-Dist: pytest-mock; extra == "dev"
Requires-Dist: ruff; extra == "dev"
Requires-Dist: sphinx; extra == "dev"
Requires-Dist: sphinx-rtd-theme; extra == "dev"
Requires-Dist: sphinx-autodoc-typehints; extra == "dev"
Requires-Dist: myst-parser; extra == "dev"
Requires-Dist: pre-commit; extra == "dev"
Requires-Dist: build; extra == "dev"
Requires-Dist: twine; extra == "dev"
Dynamic: license-file
